mailtest/__init__.py
mailtest/api.py
mailtest/client.py
mailtest/errors.py
python_mailtest-1.0.0a2.dist-info/DESCRIPTION.rst
python_mailtest-1.0.0a2.dist-info/METADATA
python_mailtest-1.0.0a2.dist-info/RECORD
python_mailtest-1.0.0a2.dist-info/WHEEL
python_mailtest-1.0.0a2.dist-info/metadata.json
python_mailtest-1.0.0a2.dist-info/top_level.txt
python_mailtest-1.0.0a2.dist-info/zip-safe
